crafty_client/__init__.py
crafty_client/crafty4.py
crafty_client/static/__init__.py
crafty_client/static/exceptions.py
crafty_client/static/routes.py
crafty_client-2.0.0.dist-info/METADATA
crafty_client-2.0.0.dist-info/WHEEL
crafty_client-2.0.0.dist-info/top_level.txt
crafty_client-2.0.0.dist-info/RECORD
