Metadata-Version: 2.1
Name: crafty_client
Version: 2.0.0
Summary: A python library for talking to Crafty Controller - a server management panel
Home-page: https://gitlab.com/crafty-controller/crafty-client
Author: Arcadia Technology, LLC.
Requires-Dist: requests
Requires-Dist: urllib3
